{
	"id": "loan-service-environment",
	"name": "Loan Service API Environment",
	"values": [
		{
			"key": "base_url",
			"value": "http://localhost:8080",
			"type": "default",
			"enabled": true
		},
		{
			"key": "loan_id",
			"value": "",
			"type": "default",
			"enabled": true
		},
		{
			"key": "borrower_id",
			"value": "test_borrower_001",
			"type": "default",
			"enabled": true
		},
		{
			"key": "investor_id",
			"value": "test_investor_001",
			"type": "default",
			"enabled": true
		},
		{
			"key": "field_validator_id",
			"value": "test_validator_001",
			"type": "default",
			"enabled": true
		},
		{
			"key": "field_officer_id",
			"value": "test_officer_001",
			"type": "default",
			"enabled": true
		},
		{
			"key": "principal_amount",
			"value": "10000.00",
			"type": "default",
			"enabled": true
		},
		{
			"key": "rate",
			"value": "5.0",
			"type": "default",
			"enabled": true
		},
		{
			"key": "roi",
			"value": "7.0",
			"type": "default",
			"enabled": true
		},
		{
			"key": "investment_amount",
			"value": "5000.00",
			"type": "default",
			"enabled": true
		},
		{
			"key": "field_validator_proof",
			"value": "https://example.com/images/validation_proof.jpg",
			"type": "default",
			"enabled": true
		},
		{
			"key": "signed_agreement_link",
			"value": "https://example.com/documents/signed_agreement.pdf",
			"type": "default",
			"enabled": true
		}
	],
	"_postman_variable_scope": "environment",
	"_postman_exported_at": "2025-08-17T11:00:00.000Z",
	"_postman_exported_using": "Postman/10.0.0"
}
